Cassiopee/__init__.py
Cassiopee-3.6.0.dist-info/LICENSE
Cassiopee-3.6.0.dist-info/METADATA
Cassiopee-3.6.0.dist-info/WHEEL
Cassiopee-3.6.0.dist-info/top_level.txt
Cassiopee-3.6.0.dist-info/RECORD
